barobo/linkbot.py
barobo/mobot.py
barobo/_comms.py
barobo/_util.py
barobo/__init__.py
barobo/lib/libsfp.dll
PyBarobo-0.1.18.dist-info/DESCRIPTION.rst
PyBarobo-0.1.18.dist-info/METADATA
PyBarobo-0.1.18.dist-info/metadata.json
PyBarobo-0.1.18.dist-info/RECORD
PyBarobo-0.1.18.dist-info/top_level.txt
PyBarobo-0.1.18.dist-info/WHEEL
