Metadata-Version: 2.0
Name: PyBarobo
Version: 0.1.18
Summary: Native Python Barobo robotics control library
Home-page: http://www.barobo.com
Author: David Ko
Author-email: david@barobo.com
License: GPL
Platform: any
Requires-Dist: pyserial (>=2.7)
